energyplus_pet/__init__.py
energyplus_pet/__main__.py
energyplus_pet/configure.py
energyplus_pet/correction_factor.py
energyplus_pet/data_manager.py
energyplus_pet/exceptions.py
energyplus_pet/runner.py
energyplus_pet/units.py
energyplus_pet/equipment/__init__.py
energyplus_pet/equipment/base.py
energyplus_pet/equipment/column_header.py
energyplus_pet/equipment/common_curves.py
energyplus_pet/equipment/equip_types.py
energyplus_pet/equipment/manager.py
energyplus_pet/equipment/wahp_cooling_curve.py
energyplus_pet/equipment/wahp_heating_curve.py
energyplus_pet/equipment/wwhp_cooling_curve.py
energyplus_pet/equipment/wwhp_heating_curve.py
energyplus_pet/examples/wahp.ods
energyplus_pet/examples/wwhp.ods
energyplus_pet/forms/__init__.py
energyplus_pet/forms/base_data_form.py
energyplus_pet/forms/basic_message_form.py
energyplus_pet/forms/catalog_plot.py
energyplus_pet/forms/comparison_plot.py
energyplus_pet/forms/constant_parameters.py
energyplus_pet/forms/correction_detail_form.py
energyplus_pet/forms/correction_summary_form.py
energyplus_pet/forms/correction_summary_widget.py
energyplus_pet/forms/header_preview.py
energyplus_pet/forms/main.py
energyplus_pet/icons/icon.icns
energyplus_pet/icons/icon.ico
energyplus_pet/icons/icon.png
energyplus_pet-0.62.dist-info/LICENSE.txt
energyplus_pet-0.62.dist-info/METADATA
energyplus_pet-0.62.dist-info/WHEEL
energyplus_pet-0.62.dist-info/entry_points.txt
energyplus_pet-0.62.dist-info/top_level.txt
energyplus_pet-0.62.dist-info/RECORD
