Metadata-Version: 2.1
Name: energyplus-pet
Version: 0.62
Summary: Parameter Estimation Tools for Generating EnergyPlus Inputs from Raw Performance Data
Home-page: https://github.com/Myoldmopar/EnergyPlusPet
Author: Edwin Lee, for NREL, for United States Department of Energy
License: ModifiedBSD
Keywords: energyplus_launch,ep_launch,EnergyPlus,eplus,Energy+,Building Simulation,Whole Building Energy Simulation,Heat Transfer,HVAC,Modeling
Platform: Linux (Tested on Ubuntu)
Platform: MacOSX
Platform: Windows
Classifier: Development Status :: 4 - Beta
Classifier: Intended Audience :: Science/Research
Classifier: Natural Language :: English
Classifier: Operating System :: OS Independent
Classifier: Programming Language :: Python :: 3 :: Only
Classifier: Topic :: Scientific/Engineering
Classifier: Topic :: Scientific/Engineering :: Physics
Classifier: Topic :: Utilities
Requires-Dist: tksheet ==7.1.8
Requires-Dist: matplotlib
Requires-Dist: scipy
Requires-Dist: PLAN-Tools >=0.5
Requires-Dist: pillow >=8.0.0
